task_list/__init__.py
task_list/__main__.py
task_list/storage_api.py
dearpygui_task_list-4.0.1.dist-info/LICENSE
dearpygui_task_list-4.0.1.dist-info/METADATA
dearpygui_task_list-4.0.1.dist-info/WHEEL
dearpygui_task_list-4.0.1.dist-info/top_level.txt
dearpygui_task_list-4.0.1.dist-info/RECORD
