Metadata-Version: 2.1
Name: dearpygui_task_list
Version: 4.0.1
Summary: A task list application, written in Python3 using the dearpygui library
Author-email: Myles Bartlett <myles@bangsparks.com>
Project-URL: Homepage, https://github.com/mylesbartlett72/Python-Task-List
Project-URL: Bug Tracker, https://github.com/mylesbartlett72/Python-Task-List/issues
Classifier: Programming Language :: Python :: 3
Classifier: License :: OSI Approved :: GNU General Public License v3 or later (GPLv3+)
Classifier: Operating System :: OS Independent
Requires-Python: >=3.7
License-File: LICENSE
